datasette_column_sum/__init__.py
datasette_column_sum-0.1a0.dist-info/LICENSE
datasette_column_sum-0.1a0.dist-info/METADATA
datasette_column_sum-0.1a0.dist-info/WHEEL
datasette_column_sum-0.1a0.dist-info/entry_points.txt
datasette_column_sum-0.1a0.dist-info/top_level.txt
datasette_column_sum-0.1a0.dist-info/RECORD
