Metadata-Version: 2.1
Name: datasette-column-sum
Version: 0.1a0
Summary: Sum the values in numeric Datasette columns
Author: Simon Willison
License: Apache-2.0
Project-URL: Homepage, https://github.com/datasette/datasette-column-sum
Project-URL: Changelog, https://github.com/datasette/datasette-column-sum/releases
Project-URL: Issues, https://github.com/datasette/datasette-column-sum/issues
Project-URL: CI, https://github.com/datasette/datasette-column-sum/actions
Classifier: Framework :: Datasette
Classifier: License :: OSI Approved :: Apache Software License
Requires-Python: >=3.8
License-File: LICENSE
Requires-Dist: datasette >=1.0a12
Provides-Extra: playwright
Requires-Dist: pytest-playwright ; extra == 'playwright'
Provides-Extra: test
Requires-Dist: pytest ; extra == 'test'
Requires-Dist: pytest-asyncio ; extra == 'test'
Requires-Dist: datasette-test ; extra == 'test'
Requires-Dist: nest-asyncio ; extra == 'test'
